SSHTunnelLibrary/SSHTunnelKeywords.py
SSHTunnelLibrary/__init__.py
SSHTunnelLibrary/version.py
robotframework_sshtunnellibrary-1.0.0.dist-info/METADATA
robotframework_sshtunnellibrary-1.0.0.dist-info/RECORD
robotframework_sshtunnellibrary-1.0.0.dist-info/WHEEL
robotframework_sshtunnellibrary-1.0.0.dist-info/top_level.txt
