Metadata-Version: 2.1
Name: robotframework-sshtunnellibrary
Version: 1.0.0
Summary: SSH Tunnel Library for Robot framework
Home-page: https://github.com/C-Squad/robotframework-sshtunnellibrary
Author: C-Squad
Author-email: csquad.dev@gmail.com
License: Apache-2.0
Platform: any
Classifier: Development Status :: 5 - Production/Stable
Classifier: License :: OSI Approved :: Apache Software License
Classifier: Operating System :: OS Independent
Classifier: Programming Language :: Python
Classifier: Programming Language :: Python :: 2.7
Classifier: Programming Language :: Python :: 3.4
Classifier: Programming Language :: Python :: 3.5
Classifier: Programming Language :: Python :: 3.6
Classifier: Topic :: Software Development :: Testing
Classifier: Framework :: Robot Framework
Classifier: Framework :: Robot Framework :: Library
Requires-Dist: robotframework
Requires-Dist: sshtunnel
